dorothy/Audio.py
dorothy/Button.py
dorothy/Dorothy.py
dorothy/DorothyShaders.py
dorothy/DorothyWindow.py
dorothy/__init__.py
dorothy/css_colours.py
dorothy/renderer/__init__.py
dorothy/renderer/batch_manager.py
dorothy/renderer/core.py
dorothy/renderer/effects.py
dorothy/renderer/geometry_cache.py
dorothy/renderer/layers.py
dorothy/renderer/primitives_2d.py
dorothy/renderer/primitives_3d.py
dorothy/renderer/state.py
dorothy/utils/__init__.py
dorothy/utils/gan_model.py
dorothy/utils/latent_util.py
dorothy/utils/magnet.py
dorothy/utils/rave_download.py
dorothy/utils/util.py
dorothy/utils/yolo_draw_utils.py
dorothy_cci-0.0.65.dist-info/LICENSE
dorothy_cci-0.0.65.dist-info/METADATA
dorothy_cci-0.0.65.dist-info/WHEEL
dorothy_cci-0.0.65.dist-info/top_level.txt
dorothy_cci-0.0.65.dist-info/RECORD
